<?xml version="1.0" encoding="utf-8"?>
<Defs>

	<SoundDef>
		<defName>Trebuchet_Launch</defName>
		<eventNames />   <context>MapOnly</context>
		<maxSimultaneous>1</maxSimultaneous>
		<subSounds>
			<li>
				<grains>
					<li Class="AudioGrain_Clip">
						<clipPath>Things/Trebuchet_Launch</clipPath>
					</li>
				</grains>
				<pitchRange>
					<min>0.9152174</min>
					<max>1.042391</max>
				</pitchRange>
			</li>
		</subSounds>
	</SoundDef>


	<SoundDef>
		<defName>Catapult_Launch</defName>
		<eventNames />   <context>MapOnly</context>
		<maxSimultaneous>1</maxSimultaneous>
		<subSounds>
			<li>
				<grains>
					<li Class="AudioGrain_Clip">
						<clipPath>Things/Catapult_Launch</clipPath>
					</li>
				</grains>
				<pitchRange>
					<min>0.9152174</min>
					<max>1.042391</max>
				</pitchRange>
			</li>
		</subSounds>
	</SoundDef>

	<SoundDef>
		<defName>Ballista_Launch</defName>
		<eventNames />   <context>MapOnly</context>
		<maxSimultaneous>1</maxSimultaneous>
		<subSounds>
			<li>
				<grains>
					<li Class="AudioGrain_Clip">
						<clipPath>Things/Ballista_Launch</clipPath>
					</li>
				</grains>
				<pitchRange>
					<min>0.9152174</min>
					<max>1.042391</max>
				</pitchRange>
			</li>
		</subSounds>
	</SoundDef>

</Defs>
